{
  "changedFilesIos": [
    "css\\index.css",
    "usersettings.html",
    "activite.html",
    "config.xml",
    "choice.html",
    "categoriesSelection.html",
    "images\\cofee.png",
    "images\\drink.png",
    "images\\game.png",
    "images\\run.png",
    "images\\movie.png",
    "scripts\\userSettings.js",
    "scripts\\mainPage.js",
    "scripts\\categoriesSelection.js"
  ],
  "deletedFilesIos": [],
  "addedPluginsIos": [],
  "deletedPluginsIos": [],
  "changedFiles": [],
  "deletedFiles": [],
  "addedPlugins": [],
  "deletedPlugins": []
}